LICENSE.txt
README.md
setup.cfg
setup.py
State_Engine.egg-info/PKG-INFO
State_Engine.egg-info/SOURCES.txt
State_Engine.egg-info/dependency_links.txt
State_Engine.egg-info/requires.txt
State_Engine.egg-info/top_level.txt
state_engine/__init__.py
state_engine/events.py
state_engine/exc.py
state_engine/machines.py
state_engine/utils.py